opencrud/__init__.py
opencrud/connection.py
opencrud/custom.py
opencrud/field.py
opencrud/filter.py
opencrud/list.py
opencrud/utils.py
opencrud/tests/__init__.py
opencrud/tests/models.py
opencrud/tests/test_connection.py
opencrud/tests/test_field.py
opencrud/tests/test_filter.py
opencrud/tests/test_list.py
graphene_django_opencrud-1.0.0.dist-info/LICENSE
graphene_django_opencrud-1.0.0.dist-info/METADATA
graphene_django_opencrud-1.0.0.dist-info/WHEEL
graphene_django_opencrud-1.0.0.dist-info/top_level.txt
graphene_django_opencrud-1.0.0.dist-info/RECORD
