Metadata-Version: 2.1
Name: graphene-django-opencrud
Version: 1.0.0
Summary: Opencrud Graphene Django implementation
Home-page: https://github.com/inspired-solutions/graphene-django-opencrud
Author: Inspired Solutions
Author-email: contacto@inspiredsolutions.pe
License: MIT
Keywords: api graphql protocol rest relay graphene opencrud
Platform: any
Classifier: Development Status :: 3 - Alpha
Classifier: Intended Audience :: Developers
Classifier: Topic :: Software Development :: Libraries
Classifier: Programming Language :: Python :: 2
Classifier: Programming Language :: Python :: 2.7
Classifier: Programming Language :: Python :: 3
Classifier: Programming Language :: Python :: 3.4
Classifier: Programming Language :: Python :: 3.5
Classifier: Programming Language :: Python :: 3.6
Classifier: Programming Language :: Python :: Implementation :: PyPy
Requires-Dist: graphene-django
Requires-Dist: django-filter (>=2)
Requires-Dist: Django (>=2)
Provides-Extra: test
Requires-Dist: coverage; extra == 'test'
Requires-Dist: django-filter (>=2); extra == 'test'
Requires-Dist: djangorestframework; extra == 'test'
Requires-Dist: graphene-django; extra == 'test'
Requires-Dist: pytest; extra == 'test'
Requires-Dist: pytest-cov; extra == 'test'
Requires-Dist: pytest-django; extra == 'test'
